AntiCAP/__init__.py
AntiCAP/core.py
AntiCAP/modules/__init__.py
AntiCAP/modules/click.py
AntiCAP/modules/detection.py
AntiCAP/modules/math_solver.py
AntiCAP/modules/ocr.py
AntiCAP/modules/rotation.py
AntiCAP/modules/similarity.py
AntiCAP/modules/slider.py
AntiCAP/utils/__init__.py
AntiCAP/utils/common.py
AntiCAP/utils/exceptions.py
AntiCAP/utils/manager.py
anticap-3.3.5.dist-info/licenses/LICENSE
anticap-3.3.5.dist-info/METADATA
anticap-3.3.5.dist-info/WHEEL
anticap-3.3.5.dist-info/top_level.txt
anticap-3.3.5.dist-info/RECORD
